CHANGES.txt
MANIFEST.in
README.txt
bootstrap.py
buildout.cfg
setup.py
docs/LICENSE.GPL
docs/LICENSE.txt
experimental/__init__.py
experimental.atrefspeedup.egg-info/PKG-INFO
experimental.atrefspeedup.egg-info/SOURCES.txt
experimental.atrefspeedup.egg-info/dependency_links.txt
experimental.atrefspeedup.egg-info/entry_points.txt
experimental.atrefspeedup.egg-info/namespace_packages.txt
experimental.atrefspeedup.egg-info/not-zip-safe
experimental.atrefspeedup.egg-info/requires.txt
experimental.atrefspeedup.egg-info/top_level.txt
experimental/atrefspeedup/__init__.py
experimental/atrefspeedup/configure.zcml
experimental/atrefspeedup/patches.py
experimental/atrefspeedup/tests/__init__.py
experimental/atrefspeedup/tests/base.py
experimental/atrefspeedup/tests/layer.py
experimental/atrefspeedup/tests/test_engine.py
experimental/atrefspeedup/tests/test_referenceable.py