Metadata-Version: 1.0
Name: experimental.atrefspeedup
Version: 1.0a6
Summary: Speedup of the Archetypes reference engine.
Home-page: http://www.jarn.com/
Author: Jarn AS
Author-email: info@jarn.com
License: GPL version 2
Keywords: plone reference speed
Platform: UNKNOWN
Classifier: Framework :: Plone
Classifier: Programming Language :: Python
